LICENSE.txt
README.md
setup.cfg
setup.py
os_file_stream_handler/file_stream_handler.py
os_file_stream_handler/test.py
os_file_stream_handler.egg-info/PKG-INFO
os_file_stream_handler.egg-info/SOURCES.txt
os_file_stream_handler.egg-info/dependency_links.txt
os_file_stream_handler.egg-info/top_level.txt