Metadata-Version: 2.1
Name: os-file-stream-handler
Version: 1.13
Summary: py file stream handling tools for os
Home-page: https://github.com/osfunapps/os-file-stream-handler-py
Author: Oz Shabat
Author-email: support@os-apps.com
License: MIT
Keywords: python,osfunapps,files,tools,utils,stream
Classifier: Development Status :: 5 - Production/Stable
Classifier: Intended Audience :: Developers
Classifier: Topic :: Software Development :: Build Tools
Classifier: License :: OSI Approved :: MIT License
Classifier: Programming Language :: Python :: 3
Classifier: Programming Language :: Python :: 3.4
Classifier: Programming Language :: Python :: 3.5
Classifier: Programming Language :: Python :: 3.6
Classifier: Programming Language :: Python :: 3.9
License-File: LICENSE.txt
